LICENSE
MANIFEST.in
README.rst
setup.cfg
setup.py
fishwxnotifys/__init__.py
fishwxnotifys/access.py
fishwxnotifys/apps.py
fishwxnotifys/config.py
fishwxnotifys/exceptions.py
fishwxnotifys/tasks.py
fishwxnotifys.egg-info/PKG-INFO
fishwxnotifys.egg-info/SOURCES.txt
fishwxnotifys.egg-info/dependency_links.txt
fishwxnotifys.egg-info/requires.txt
fishwxnotifys.egg-info/top_level.txt